MANIFEST.in
README.md
setup.py
hehey_hvalidation.egg-info/PKG-INFO
hehey_hvalidation.egg-info/SOURCES.txt
hehey_hvalidation.egg-info/dependency_links.txt
hehey_hvalidation.egg-info/top_level.txt
hvalidation/LICENSE
hvalidation/README.md
hvalidation/__init__.py
hvalidation/validation.py
hvalidation/base/Rule.py
hvalidation/base/ValidateResult.py
hvalidation/base/Validator.py
hvalidation/base/__init__.py
hvalidation/utils/ValidUtil.py
hvalidation/utils/__init__.py
hvalidation/validator/BooleanValidator.py
hvalidation/validator/CharValidator.py
hvalidation/validator/ChineseValidator.py
hvalidation/validator/CompareFieldValidator.py
hvalidation/validator/CompareValidator.py
hvalidation/validator/CurrencyValidator.py
hvalidation/validator/DateValidator.py
hvalidation/validator/DefaultValidator.py
hvalidation/validator/EmailValidator.py
hvalidation/validator/EmptyValidator.py
hvalidation/validator/EnglishValidator.py
hvalidation/validator/EqualValidator.py
hvalidation/validator/FloatValidator.py
hvalidation/validator/FuncValidator.py
hvalidation/validator/InValidator.py
hvalidation/validator/IntValidator.py
hvalidation/validator/IpValidator.py
hvalidation/validator/LengthValidator.py
hvalidation/validator/ListValidator.py
hvalidation/validator/RangeDateValidator.py
hvalidation/validator/RangeLengthValidator.py
hvalidation/validator/RangeValidator.py
hvalidation/validator/RegularValidator.py
hvalidation/validator/RequiredValidator.py
hvalidation/validator/TelValidator.py
hvalidation/validator/UrlValidator.py
hvalidation/validator/__init__.py