Metadata-Version: 2.1
Name: hehey-hvalidation
Version: 1.2.3
Summary: hehey-hvalidation 是一个python 全面的验证器工具类.
Home-page: https://gitee.com/chinahehe/hehey-hvalidation
Author: 13564768842
Author-email: chinabluexfw@163.com
License: UNKNOWN
Platform: UNKNOWN
